scioptim/__init__.py
scioptim/base.py
scioptim/bayesian.py
scioptim/evolutionary.py
scioptim/function_based.py
scioptim/grid_based.py
scioptim/mixed_optimizer.py
scioptim/optuna_optimizer.py
scioptim/plotting.py
scioptim/random_search.py
scioptim/stochastic.py
scioptim/test_objectives/__init__.py
scioptim/test_objectives/base.py
scioptim/test_objectives/common.py
scioptim/test_objectives/gaussian.py
scioptim/test_objectives/pybenchfunction/__init__.py
scioptim/test_objectives/pybenchfunction/function.py
scioptim/test_objectives/pybenchfunction/generate.py
scioptim/utils.py
scioptim-0.0.20.dist-info/METADATA
scioptim-0.0.20.dist-info/WHEEL
scioptim-0.0.20.dist-info/RECORD
